mediumbackup/__init__.py
mediumbackup/__main__.py
tests/__init__.py
tests/__main__.py
mediumbackup-1.1.2.dist-info/LICENSE.txt
mediumbackup-1.1.2.dist-info/METADATA
mediumbackup-1.1.2.dist-info/WHEEL
mediumbackup-1.1.2.dist-info/top_level.txt
mediumbackup-1.1.2.dist-info/RECORD
