Metadata-Version: 2.1
Name: mediumbackup
Version: 1.1.2
Summary: Backup your Medium Stories.
Home-page: https://github.com/lucafrance/mediumbackup
Author: Luca Franceschini
Author-email: luca.france@outlook.com
License: MIT License
Platform: UNKNOWN
Classifier: Programming Language :: Python :: 3
Classifier: License :: OSI Approved :: MIT License
Classifier: Operating System :: OS Independent
Requires-Python: >=3.8
Requires-Dist: python-medium
Requires-Dist: markdownify
Requires-Dist: beautifulsoup4
Requires-Dist: requests
